topsis/__init__.py
topsis/__main__.py
Topsis_Shivane_102203191-1.0.0.dist-info/LICENSE
Topsis_Shivane_102203191-1.0.0.dist-info/METADATA
Topsis_Shivane_102203191-1.0.0.dist-info/WHEEL
Topsis_Shivane_102203191-1.0.0.dist-info/entry_points.txt
Topsis_Shivane_102203191-1.0.0.dist-info/top_level.txt
Topsis_Shivane_102203191-1.0.0.dist-info/RECORD
