Metadata-Version: 2.2
Name: Topsis_Shivane_102203191
Version: 1.0.0
Summary: Ranking alternatives based on similarity.
Home-page: https://github.com/shivane1/Topsis-Shivane-102203191
Author: Shivane Kapoor
Author-email: shivane5600@gmail.com
License: MIT
Classifier: License :: OSI Approved :: MIT License
Classifier: Programming Language :: Python :: 3.6
Classifier: Programming Language :: Python :: 3.7
Classifier: Programming Language :: Python :: 3.8
License-File: LICENSE
Dynamic: author
Dynamic: author-email
Dynamic: classifier
Dynamic: description
Dynamic: description-content-type
Dynamic: home-page
Dynamic: license
Dynamic: summary
